{"Name": "instance06--MRA--mrur-8-pre1-4-2-4#3", "Horizon": 324, "TargetJob": 60, "Resources": [{"Type": "R", "Id": 1, "Capacity": 24, "Availability": {"Periodical": [{"Start": 14, "End": 22, "Capacity": 24}], "Additions": [], "Migrations": []}}, {"Type": "R", "Id": 2, "Capacity": 21, "Availability": {"Periodical": [{"Start": 14, "End": 22, "Capacity": 21}], "Additions": [], "Migrations": []}}, {"Type": "R", "Id": 3, "Capacity": 24, "Availability": {"Periodical": [{"Start": 14, "End": 22, "Capacity": 24}], "Additions": [], "Migrations": []}}, {"Type": "R", "Id": 4, "Capacity": 20, "Availability": {"Periodical": [{"Start": 14, "End": 22, "Capacity": 20}], "Additions": [], "Migrations": []}}], "Projects": [{"Id": 1, "Due date": 61, "Tardiness cost": 22}], "Jobs": [{"Id": 1, "Duration": 0, "Resource consumption": {"Consumptions": {"R1": 0, "R2": 0, "R3": 0, "R4": 0}}, "Successors": [3], "Due date": 0, "Completed": false}, {"Id": 2, "Duration": 2, "Resource consumption": {"Consumptions": {"R1": 6, "R2": 8, "R3": 1, "R4": 8}}, "Successors": [5], "Due date": 0, "Completed": false}, {"Id": 3, "Duration": 6, "Resource consumption": {"Consumptions": {"R1": 7, "R2": 3, "R3": 6, "R4": 7}}, "Successors": [18], "Due date": 0, "Completed": false}, {"Id": 4, "Duration": 1, "Resource consumption": {"Consumptions": {"R1": 9, "R2": 8, "R3": 8, "R4": 4}}, "Successors": [10], "Due date": 0, "Completed": false}, {"Id": 5, "Duration": 5, "Resource consumption": {"Consumptions": {"R1": 4, "R2": 7, "R3": 2, "R4": 5}}, "Successors": [19], "Due date": 0, "Completed": false}, {"Id": 6, "Duration": 6, "Resource consumption": {"Consumptions": {"R1": 4, "R2": 5, "R3": 6, "R4": 6}}, "Successors": [12], "Due date": 0, "Completed": false}, {"Id": 7, "Duration": 1, "Resource consumption": {"Consumptions": {"R1": 4, "R2": 4, "R3": 1, "R4": 1}}, "Successors": [44], "Due date": 0, "Completed": false}, {"Id": 8, "Duration": 2, "Resource consumption": {"Consumptions": {"R1": 4, "R2": 10, "R3": 5, "R4": 8}}, "Successors": [16], "Due date": 0, "Completed": false}, {"Id": 9, "Duration": 5, "Resource consumption": {"Consumptions": {"R1": 10, "R2": 10, "R3": 8, "R4": 2}}, "Successors": [57], "Due date": 0, "Completed": false}, {"Id": 10, "Duration": 4, "Resource consumption": {"Consumptions": {"R1": 3, "R2": 1, "R3": 1, "R4": 10}}, "Successors": [49], "Due date": 0, "Completed": false}, {"Id": 11, "Duration": 5, "Resource consumption": {"Consumptions": {"R1": 8, "R2": 1, "R3": 4, "R4": 5}}, "Successors": [13], "Due date": 0, "Completed": false}, {"Id": 12, "Duration": 6, "Resource consumption": {"Consumptions": {"R1": 7, "R2": 6, "R3": 7, "R4": 6}}, "Successors": [22], "Due date": 0, "Completed": false}, {"Id": 13, "Duration": 5, "Resource consumption": {"Consumptions": {"R1": 5, "R2": 2, "R3": 1, "R4": 8}}, "Successors": [25], "Due date": 0, "Completed": false}, {"Id": 14, "Duration": 7, "Resource consumption": {"Consumptions": {"R1": 7, "R2": 9, "R3": 4, "R4": 2}}, "Successors": [45], "Due date": 0, "Completed": false}, {"Id": 15, "Duration": 4, "Resource consumption": {"Consumptions": {"R1": 4, "R2": 8, "R3": 6, "R4": 2}}, "Successors": [35], "Due date": 0, "Completed": false}, {"Id": 16, "Duration": 1, "Resource consumption": {"Consumptions": {"R1": 10, "R2": 4, "R3": 10, "R4": 2}}, "Successors": [51], "Due date": 0, "Completed": false}, {"Id": 17, "Duration": 1, "Resource consumption": {"Consumptions": {"R1": 4, "R2": 5, "R3": 6, "R4": 3}}, "Successors": [21], "Due date": 0, "Completed": false}, {"Id": 18, "Duration": 4, "Resource consumption": {"Consumptions": {"R1": 4, "R2": 4, "R3": 8, "R4": 4}}, "Successors": [34], "Due date": 0, "Completed": false}, {"Id": 19, "Duration": 5, "Resource consumption": {"Consumptions": {"R1": 6, "R2": 1, "R3": 3, "R4": 7}}, "Successors": [32], "Due date": 0, "Completed": false}, {"Id": 20, "Duration": 1, "Resource consumption": {"Consumptions": {"R1": 4, "R2": 8, "R3": 7, "R4": 4}}, "Successors": [28], "Due date": 0, "Completed": false}, {"Id": 21, "Duration": 2, "Resource consumption": {"Consumptions": {"R1": 2, "R2": 2, "R3": 4, "R4": 5}}, "Successors": [59], "Due date": 0, "Completed": false}, {"Id": 22, "Duration": 1, "Resource consumption": {"Consumptions": {"R1": 9, "R2": 3, "R3": 9, "R4": 10}}, "Successors": [23], "Due date": 0, "Completed": false}, {"Id": 23, "Duration": 3, "Resource consumption": {"Consumptions": {"R1": 3, "R2": 3, "R3": 1, "R4": 5}}, "Successors": [53], "Due date": 0, "Completed": false}, {"Id": 24, "Duration": 1, "Resource consumption": {"Consumptions": {"R1": 8, "R2": 5, "R3": 7, "R4": 6}}, "Successors": [27], "Due date": 0, "Completed": false}, {"Id": 25, "Duration": 5, "Resource consumption": {"Consumptions": {"R1": 9, "R2": 10, "R3": 8, "R4": 6}}, "Successors": [26], "Due date": 0, "Completed": false}, {"Id": 26, "Duration": 5, "Resource consumption": {"Consumptions": {"R1": 10, "R2": 8, "R3": 10, "R4": 10}}, "Successors": [36], "Due date": 0, "Completed": false}, {"Id": 27, "Duration": 6, "Resource consumption": {"Consumptions": {"R1": 8, "R2": 1, "R3": 5, "R4": 6}}, "Successors": [42], "Due date": 0, "Completed": false}, {"Id": 28, "Duration": 8, "Resource consumption": {"Consumptions": {"R1": 10, "R2": 6, "R3": 6, "R4": 1}}, "Successors": [54], "Due date": 0, "Completed": false}, {"Id": 29, "Duration": 2, "Resource consumption": {"Consumptions": {"R1": 8, "R2": 1, "R3": 9, "R4": 5}}, "Successors": [51], "Due date": 0, "Completed": false}, {"Id": 30, "Duration": 4, "Resource consumption": {"Consumptions": {"R1": 9, "R2": 6, "R3": 4, "R4": 7}}, "Successors": [33], "Due date": 0, "Completed": false}, {"Id": 31, "Duration": 1, "Resource consumption": {"Consumptions": {"R1": 1, "R2": 3, "R3": 4, "R4": 1}}, "Successors": [39], "Due date": 0, "Completed": false}, {"Id": 32, "Duration": 5, "Resource consumption": {"Consumptions": {"R1": 7, "R2": 4, "R3": 2, "R4": 9}}, "Successors": [], "Due date": 70, "Completed": false}, {"Id": 33, "Duration": 1, "Resource consumption": {"Consumptions": {"R1": 6, "R2": 10, "R3": 10, "R4": 7}}, "Successors": [55], "Due date": 0, "Completed": false}, {"Id": 34, "Duration": 2, "Resource consumption": {"Consumptions": {"R1": 8, "R2": 3, "R3": 3, "R4": 5}}, "Successors": [48], "Due date": 0, "Completed": false}, {"Id": 35, "Duration": 6, "Resource consumption": {"Consumptions": {"R1": 8, "R2": 3, "R3": 6, "R4": 3}}, "Successors": [58], "Due date": 0, "Completed": false}, {"Id": 36, "Duration": 1, "Resource consumption": {"Consumptions": {"R1": 1, "R2": 4, "R3": 3, "R4": 9}}, "Successors": [43], "Due date": 0, "Completed": false}, {"Id": 37, "Duration": 2, "Resource consumption": {"Consumptions": {"R1": 2, "R2": 3, "R3": 9, "R4": 9}}, "Successors": [44], "Due date": 0, "Completed": false}, {"Id": 38, "Duration": 2, "Resource consumption": {"Consumptions": {"R1": 4, "R2": 8, "R3": 2, "R4": 1}}, "Successors": [42], "Due date": 0, "Completed": false}, {"Id": 39, "Duration": 2, "Resource consumption": {"Consumptions": {"R1": 5, "R2": 9, "R3": 7, "R4": 7}}, "Successors": [57], "Due date": 0, "Completed": false}, {"Id": 40, "Duration": 7, "Resource consumption": {"Consumptions": {"R1": 3, "R2": 5, "R3": 9, "R4": 2}}, "Successors": [44], "Due date": 0, "Completed": false}, {"Id": 41, "Duration": 1, "Resource consumption": {"Consumptions": {"R1": 9, "R2": 5, "R3": 10, "R4": 10}}, "Successors": [52], "Due date": 0, "Completed": false}, {"Id": 42, "Duration": 7, "Resource consumption": {"Consumptions": {"R1": 1, "R2": 6, "R3": 2, "R4": 10}}, "Successors": [52], "Due date": 0, "Completed": false}, {"Id": 43, "Duration": 8, "Resource consumption": {"Consumptions": {"R1": 4, "R2": 1, "R3": 2, "R4": 1}}, "Successors": [55], "Due date": 0, "Completed": false}, {"Id": 44, "Duration": 5, "Resource consumption": {"Consumptions": {"R1": 9, "R2": 6, "R3": 5, "R4": 5}}, "Successors": [52], "Due date": 0, "Completed": false}, {"Id": 45, "Duration": 3, "Resource consumption": {"Consumptions": {"R1": 6, "R2": 3, "R3": 9, "R4": 5}}, "Successors": [54], "Due date": 0, "Completed": false}, {"Id": 46, "Duration": 1, "Resource consumption": {"Consumptions": {"R1": 7, "R2": 8, "R3": 7, "R4": 10}}, "Successors": [53], "Due date": 0, "Completed": false}, {"Id": 47, "Duration": 6, "Resource consumption": {"Consumptions": {"R1": 2, "R2": 6, "R3": 10, "R4": 6}}, "Successors": [51], "Due date": 0, "Completed": false}, {"Id": 48, "Duration": 4, "Resource consumption": {"Consumptions": {"R1": 9, "R2": 1, "R3": 1, "R4": 8}}, "Successors": [53], "Due date": 0, "Completed": false}, {"Id": 49, "Duration": 4, "Resource consumption": {"Consumptions": {"R1": 2, "R2": 7, "R3": 8, "R4": 4}}, "Successors": [50], "Due date": 0, "Completed": false}, {"Id": 50, "Duration": 7, "Resource consumption": {"Consumptions": {"R1": 10, "R2": 1, "R3": 4, "R4": 1}}, "Successors": [55], "Due date": 0, "Completed": false}, {"Id": 51, "Duration": 5, "Resource consumption": {"Consumptions": {"R1": 4, "R2": 7, "R3": 7, "R4": 9}}, "Successors": [61], "Due date": 0, "Completed": false}, {"Id": 52, "Duration": 8, "Resource consumption": {"Consumptions": {"R1": 1, "R2": 6, "R3": 4, "R4": 10}}, "Successors": [58], "Due date": 0, "Completed": false}, {"Id": 53, "Duration": 5, "Resource consumption": {"Consumptions": {"R1": 9, "R2": 3, "R3": 9, "R4": 1}}, "Successors": [60], "Due date": 0, "Completed": false}, {"Id": 54, "Duration": 8, "Resource consumption": {"Consumptions": {"R1": 4, "R2": 4, "R3": 8, "R4": 10}}, "Successors": [], "Due date": 94, "Completed": false}, {"Id": 55, "Duration": 1, "Resource consumption": {"Consumptions": {"R1": 8, "R2": 2, "R3": 1, "R4": 6}}, "Successors": [57], "Due date": 0, "Completed": false}, {"Id": 56, "Duration": 5, "Resource consumption": {"Consumptions": {"R1": 8, "R2": 6, "R3": 4, "R4": 1}}, "Successors": [58], "Due date": 0, "Completed": false}, {"Id": 57, "Duration": 2, "Resource consumption": {"Consumptions": {"R1": 2, "R2": 8, "R3": 1, "R4": 4}}, "Successors": [], "Due date": 214, "Completed": false}, {"Id": 58, "Duration": 1, "Resource consumption": {"Consumptions": {"R1": 7, "R2": 9, "R3": 6, "R4": 1}}, "Successors": [], "Due date": 166, "Completed": false}, {"Id": 59, "Duration": 8, "Resource consumption": {"Consumptions": {"R1": 3, "R2": 1, "R3": 1, "R4": 4}}, "Successors": [], "Due date": 46, "Completed": false}, {"Id": 60, "Duration": 6, "Resource consumption": {"Consumptions": {"R1": 5, "R2": 7, "R3": 5, "R4": 5}}, "Successors": [], "Due date": 70, "Completed": false}, {"Id": 61, "Duration": 7, "Resource consumption": {"Consumptions": {"R1": 9, "R2": 5, "R3": 7, "R4": 1}}, "Successors": [62], "Due date": 0, "Completed": false}, {"Id": 62, "Duration": 0, "Resource consumption": {"Consumptions": {"R1": 0, "R2": 0, "R3": 0, "R4": 0}}, "Successors": [], "Due date": 94, "Completed": false}], "Components": [{"Root job": 32, "Weight": 1}, {"Root job": 54, "Weight": 1}, {"Root job": 57, "Weight": 1}, {"Root job": 58, "Weight": 1}, {"Root job": 59, "Weight": 1}, {"Root job": 60, "Weight": 3}, {"Root job": 62, "Weight": 1}]}